internal/__init__.py
internal/base_config.py
internal/base_factory.py
internal/cache_redis.py
internal/common_enum/__init__.py
internal/common_enum/car_relation_type.py
internal/common_enum/description_type.py
internal/common_enum/device_code.py
internal/common_enum/event_code.py
internal/common_enum/lpr_direction.py
internal/common_enum/notify_type.py
internal/common_enum/operator_type.py
internal/common_enum/order_type.py
internal/common_enum/point_type.py
internal/common_enum/websocket_channel.py
internal/const.py
internal/database.py
internal/exception/__init__.py
internal/exception/app_exception.py
internal/exception/base_exception.py
internal/exception/internal_exception.py
internal/ext/__init__.py
internal/ext/amazon/__init__.py
internal/ext/amazon/aws/__init__.py
internal/ext/amazon/aws/const.py
internal/http/__init__.py
internal/http/requests.py
internal/http/responses.py
internal/interface/__init__.py
internal/interface/base_interface.py
internal/middleware/__init__.py
internal/middleware/log_request.py
internal/model/__init__.py
internal/model/base_model.py
internal/model/operate.py
internal/utils.py
internal/validator_utils.py
internal-1.1.48.8.dist-info/METADATA
internal-1.1.48.8.dist-info/WHEEL
internal-1.1.48.8.dist-info/RECORD
