Metadata-Version: 2.3
Name: internal
Version: 1.1.48.8
Summary: 
Author: Ray
Author-email: ray@cruisys.com
Requires-Python: >=3.11,<4.0
Classifier: Programming Language :: Python :: 3
Classifier: Programming Language :: Python :: 3.11
Classifier: Programming Language :: Python :: 3.12
Classifier: Programming Language :: Python :: 3.13
Requires-Dist: arrow (>=1.3.0,<2.0.0)
Requires-Dist: asgi-correlation-id (>=4.3.4,<5.0.0)
Requires-Dist: beanie (>=1.29.0,<2.0.0)
Requires-Dist: dictdiffer (>=0.9.0,<0.10.0)
Requires-Dist: fastapi (>=0.115.6,<0.116.0)
Requires-Dist: httpx (>=0.28.1,<0.29.0)
Requires-Dist: pydantic-settings (>=2.7.1,<3.0.0)
Requires-Dist: pytest (>=8.4.1,<9.0.0)
Requires-Dist: pytest-asyncio (>=1.0.0,<2.0.0)
Requires-Dist: pytest-sugar (>=1.0.0,<2.0.0)
Requires-Dist: redis (>=5.2.1,<6.0.0)
Requires-Dist: uvicorn (>=0.34.0,<0.35.0)
Requires-Dist: watchtower (>=3.3.1,<4.0.0)
